{"32": {"becameSuitTime": 1473552463.786, "savedBy": null, "track": "m", "numFloors": 3, "difficulty": 6, "state": "suit", "block": 32}, "37": {"becameSuitTime": 1473551288.679, "savedBy": null, "track": "m", "numFloors": 3, "difficulty": 6, "state": "suit", "block": 37}, "38": {"becameSuitTime": 1473552412.594, "savedBy": null, "track": "l", "numFloors": 3, "difficulty": 4, "state": "suit", "block": 38}, "10": {"becameSuitTime": 1473551288.68, "savedBy": null, "track": "l", "numFloors": 3, "difficulty": 6, "state": "suit", "block": 10}, "15": {"becameSuitTime": 1473553545.295, "savedBy": null, "track": "m", "numFloors": 3, "difficulty": 5, "state": "suit", "block": 15}, "19": {"becameSuitTime": 1473551288.678, "savedBy": null, "track": "s", "numFloors": 4, "difficulty": 7, "state": "suit", "block": 19}, "22": {"becameSuitTime": 1473551288.679, "savedBy": null, "track": "m", "numFloors": 4, "difficulty": 6, "state": "suit", "block": 22}, "24": {"becameSuitTime": 1473553601.28, "savedBy": null, "track": "l", "numFloors": 5, "difficulty": 6, "state": "suit", "block": 24}, "29": {"becameSuitTime": 1473553580.516, "savedBy": null, "track": "s", "numFloors": 4, "difficulty": 5, "state": "suit", "block": 29}, "31": {"becameSuitTime": 1473552457.797, "savedBy": null, "track": "s", "numFloors": 3, "difficulty": 5, "state": "suit", "block": 31}}